[
  {
    "type": "group",
    "label": {
      "en": "Server settings",
      "se": "Serverinställningar"
    },
    "children": [
      {
        "$extends": "ip"
      },
      {
        "$extends": "port"
      },
      {
        "$extends": "username"
      },
      {
        "$extends": "password"
      },
      {
        "$extends": "interval"
      }
    ]
  },
  {
    "type": "group",
    "label": { "en": "Power", "sv": "Effekt" },
    "children": [
      {
        "id": "estimate_power",
        "type": "checkbox",
        "label": { "en": "Estimate power usage", "sv": "Beräkna effekt" },
        "value": false,
        "hint": {
          "en": "Enable this to estimate output power from UPS nominal wattage.",
          "sv": "Aktivera för att beräkna utgångseffekt från UPS nominella effekt."
        },
        "highlight": true
      },
      {
        "id": "watt_nominal",
        "type": "number",
        "label": { "en": "Nominal Wattage", "sv": "Nominell effekt" },
        "hint": {
          "en": "Only used when 'Estimate power usage' is enabled.",
          "sv": "Används endast när 'Beräkna effekt' är aktiverat."
        },
        "value": 1000,
        "min": 1,
        "required": false
      }
    ]
  }
]
